mailersend/__init__.py
mailersend/activity/__init__.py
mailersend/analytics/__init__.py
mailersend/api_quota/__init__.py
mailersend/base/__init__.py
mailersend/base/base.py
mailersend/domains/__init__.py
mailersend/email_verification/__init__.py
mailersend/emails/__init__.py
mailersend/inbound_routing/__init__.py
mailersend/messages/__init__.py
mailersend/recipients/__init__.py
mailersend/scheduled_messages/__init__.py
mailersend/sender_identities/__init__.py
mailersend/sms_activity/__init__.py
mailersend/sms_inbounds/__init__.py
mailersend/sms_messages/__init__.py
mailersend/sms_phone_numbers/__init__.py
mailersend/sms_recipients/__init__.py
mailersend/sms_sending/__init__.py
mailersend/sms_webhooks/__init__.py
mailersend/templates/__init__.py
mailersend/tokens/__init__.py
mailersend/utils/__init__.py
mailersend/webhooks/__init__.py
mailersend-0.5.7.dist-info/LICENSE
mailersend-0.5.7.dist-info/METADATA
mailersend-0.5.7.dist-info/WHEEL
mailersend-0.5.7.dist-info/RECORD
