Metadata-Version: 2.1
Name: mailersend
Version: 0.5.7
Summary: The official MailerSend Python SDK
Keywords: mailersend,mail
Author: Igor Hrček
Author-email: igor@mailerlite.com
Requires-Python: >=3.8,<4.0
Classifier: Programming Language :: Python :: 3
Classifier: Programming Language :: Python :: 3.8
Classifier: Programming Language :: Python :: 3.9
Classifier: Programming Language :: Python :: 3.10
Classifier: Programming Language :: Python :: 3.11
Classifier: Programming Language :: Python :: 3.12
Requires-Dist: requests (>=2.25.0,<3.0.0)
